<annotation>
	<folder>train4</folder>
	<filename>Screen-Shot-2018-08-21-at-8.06.19-AM-2.png</filename>
	<path>C:\Users\Woradej\Desktop\train4\Screen-Shot-2018-08-21-at-8.06.19-AM-2.png</path>
	<source>
		<database>Unknown</database>
	</source>
	<size>
		<width>800</width>
		<height>600</height>
		<depth>3</depth>
	</size>
	<segmented>0</segmented>
	<object>
		<name>slow</name>
		<pose>Unspecified</pose>
		<truncated>0</truncated>
		<difficult>0</difficult>
		<bndbox>
			<xmin>552</xmin>
			<ymin>72</ymin>
			<xmax>715</xmax>
			<ymax>229</ymax>
		</bndbox>
	</object>
</annotation>
